{"cameraMode":{"drawMode":0,"name":"Shaded","section":"Shading Mode"},"sceneLighting":false,"audioPlay":false,"sceneViewState":{"showFog":true,"showMaterialUpdate":false,"showSkybox":false,"showFlares":true,"showImageEffects":true,"showParticleSystems":true},"in2DMode":false,"pivot":{"x":0.28397080302238467,"y":1.265545129776001,"z":-0.2745332717895508},"rotation":{"x":0.0001537601201562211,"y":-0.9998096823692322,"z":-0.008688786067068577,"w":-0.017706023529171945},"size":1.438276767730713,"orthographic":false}